Workbook

Sheet Asignacion
C2: OPERACION - Coopmorteros | N2: 2026
Y3: OPERACIÓN COOPMORTEROS - Hace referencia a la cantidad del tiempo que el personal de IT esta disponible para soportar y mantener las unidades de negocio que ya se encuentran operativas y facturando.
G4: =$E$24*H23 -> 3779248.4 | I4: =$E$24*J23 -> 2205742.3 | K4: =$E$24*L23 -> 2932054.4 | M4: =$E$24*N23 -> 1203584.7 | O4: =$E$24*P23 -> 165813.61 | Q4: =$E$24*R23 -> 0 | S4: =$E$24*T23 -> 0 | U4: =$E$24*V23 -> 165813.61
D5: Costo Laboral % | E5: Horas asignadas | F5: Asignado $$ operación | G5: Adm. | I5: Energia | K5: Agua | M5: Tele. | O5: Canal 50 | Q5: CAC | S5: Alm. Taller. | U5: Serv. Sociales
G6: Hs. Asignadas | H6: Impacto $$ | I6: Hs. Asignadas | J6: Impacto $$ | K6: Hs. Asignadas | L6: Impacto $$ | M6: Hs. Asignadas | N6: Impacto $$ | O6: Hs. Asignadas | P6: Impacto $$ | Q6: Hs. Asignadas | R6: Impacto $$ | S6: Hs. Asignadas | T6: Impacto $$ | U6: Hs. Asignadas | V6: Impacto $$
Y7: Semana 1 - 05 al 11 | Z7: Semana 2 - 12 al 18 | AA7: Semana 3 -19 al 25 | AB7: Semana 4 - 26 al 31
B8: Enero 2026 | C8: Leonardo Depetris | D8: 0.1913 | E8: 0.55 | F8: 0.105215 | G8: 0.15 | H8: 0.028695 | I8: 0 | J8: 0 | K8: 0.4 | L8: 0.07652 | M8: 0 | N8: 0 | O8: 0 | P8: 0 | Q8: 0 | R8: 0 | S8: 0 | T8: 0 | U8: 0 | V8: 0 | Y8: Gestiones Cooptech / Accionamiento bombeo de crudo / Viaje Marcos Juarez / Diseño +Agua | Z8: Presupuesto y presentación Marcos Juarez / Indicadores y variables calculadas +Agua / Reparación en cisterna de ósmosis | AA8: Informe triple impacto / Testing control de bombas / Chapas Santa Rosa | AB8: VACACIONES
C9: Claudio Bottero | D9: 0.1299 | E9: 0.5 | F9: 0.06495 | G9: 0.2 | H9: 0.02598 | I9: 0 | J9: 0 | K9: 0 | L9: 0 | M9: 0.2 | N9: 0.02598 | O9: 0.05 | P9: 0.006495 | Q9: 0 | R9: 0 | S9: 0 | T9: 0 | U9: 0.05 | V9: 0.006495 | Y9: Trabajos varios datacenter / Cloudflare Unquillo / DB reloj fichero / reclamo ADIT / rack sepelio | Z9: MKT Castelli / HLS Bingo 9 / Actualización K8S / Ajustes tacural | AA9: MKT Santa Rosa Starlink / Actualiz. MQTT / Migración VMS proxmox / DB O.V. (Emi. Marangoni) | AB9: Act. Unquillo / VM nueva MQTT / reunión B1Tech / server facturas Porteña
C10: Carola Clausen | D10: 0.1231 | E10: 0 | F10: 0 | G10: 0 | H10: 0 | I10: 0 | J10: 0 | K10: 0 | L10: 0 | M10: 0 | N10: 0 | O10: 0 | P10: 0 | Q10: 0 | R10: 0 | S10: 0 | T10: 0 | U10: 0 | V10: 0 | Y10: VACACIONES | Z10: VACACIONES | AA10: VACACIONES | AB10: Ventas Cooptech
C11: Lorenzo Depetris | D11: 0.1328 | E11: 0.4 | F11: 0.05312 | G11: 0 | H11: 0 | I11: 0.3 | J11: 0.03984 | K11: 0.1 | L11: 0.01328 | M11: 0 | N11: 0 | O11: 0 | P11: 0 | Q11: 0 | R11: 0 | S11: 0 | T11: 0 | U11: 0 | V11: 0 | Y11: Sensor ultrasónico / Soporte remoto Ucacha | Z11: Sensor ultrasónico / Soporte remoto Ucacha / Problema reconectadores | AA11: Soporte remoto Ucacha / Lector de pulsos / Problema reconectadores | AB11: Problema reconectadores / Viaje Santa Rosa
C12: Juan Gonzalez | D12: 0.1411 | E12: 0.25 | F12: 0.035275 | G12: 0 | H12: 0 | I12: 0.1 | J12: 0.01411 | K12: 0 | L12: 0 | M12: 0.15 | N12: 0.021165 | O12: 0 | P12: 0 | Q12: 0 | R12: 0 | S12: 0 | T12: 0 | U12: 0 | V12: 0 | Y12: VACACIONES | Z12: Reconecta Desktop | AA12: Actualizaciones Provision / Alarmas Deadmen | AB12: Alarmas Deadmen / Configuración K8S
C13: Julieta Costamagna | D13: 0.1167 | E13: 0.8 | F13: 0.09336 | G13: 0.8 | H13: 0.09336 | I13: 0 | J13: 0 | K13: 0 | L13: 0 | M13: 0 | N13: 0 | O13: 0 | P13: 0 | Q13: 0 | R13: 0 | S13: 0 | T13: 0 | U13: 0 | V13: 0 | Y13: O.V. Pña / Web Unquillo /Módulo recupero de materiales | Z13: Módulo recupero de materiales / Módulo facturas proveedores | AA13: Módulo factura proveedores / acueducto | AB13: Módulo factura proveedores / acueducto / recupero de materiales
C14: Agustin Aressi | D14: 0.1002 | E14: 0.25 | F14: 0.02505 | G14: 0 | H14: 0 | I14: 0 | J14: 0 | K14: 0.25 | L14: 0.02505 | M14: 0 | N14: 0 | O14: 0 | P14: 0 | Q14: 0 | R14: 0 | S14: 0 | T14: 0 | U14: 0 | V14: 0 | Y14: Nuevas funcionalidades +Agua: optimización de gráficos | Z14: Nuevas funcionalidades +Agua: órdebenes bombeo | AA14: Nuevas funcionalidades +Agua: múltiple led /modificación microservicios | AB14: Nuevas funcionalidades +Agua: Rio 3°
C15: Matías Gandino | D15: 0.0649 | E15: 0.5 | F15: 0.03245 | G15: 0 | H15: 0 | I15: 0.5 | J15: 0.03245 | K15: 0 | L15: 0 | M15: 0 | N15: 0 | O15: 0 | P15: 0 | Q15: 0 | R15: 0 | S15: 0 | T15: 0 | U15: 0 | V15: 0 | Y15: Sensores ultrasónicos / Analizadores de red | Z15: Analizadores de red / Implementación Santa Rosa | AA15: Analizadores de red | AB15: Analizadores de red / Implementación Santa Rosa
C16: xxx | D16: 0 | E16: 0 | F16: 0 | G16: 0 | H16: 0 | I16: 0 | J16: 0 | K16: 0 | L16: 0 | M16: 0 | N16: 0 | O16: 0 | P16: 0 | Q16: 0 | R16: 0 | S16: 0 | T16: 0 | U16: 0 | V16: 0
C17: xxx | D17: 0 | E17: 0 | F17: 0 | G17: 0 | H17: 0 | I17: 0 | J17: 0 | K17: 0 | L17: 0 | M17: 0 | N17: 0 | O17: 0 | P17: 0 | Q17: 0 | R17: 0 | S17: 0 | T17: 0 | U17: 0 | V17: 0
C18: xxx | D18: 0 | E18: 0 | F18: 0 | G18: 0 | H18: 0 | I18: 0 | J18: 0 | K18: 0 | L18: 0 | M18: 0 | N18: 0 | O18: 0 | P18: 0 | Q18: 0 | R18: 0 | S18: 0 | T18: 0 | U18: 0 | V18: 0
C19: xxx | D19: 0 | E19: 0 | F19: 0 | G19: 0 | H19: 0 | I19: 0 | J19: 0 | K19: 0 | L19: 0 | M19: 0 | N19: 0 | O19: 0 | P19: 0 | Q19: 0 | R19: 0 | S19: 0 | T19: 0 | U19: 0 | V19: 0
C20: xxx | D20: 0 | E20: 0 | F20: 0 | G20: 0 | H20: 0 | I20: 0 | J20: 0 | K20: 0 | L20: 0 | M20: 0 | N20: 0 | O20: 0 | P20: 0 | Q20: 0 | R20: 0 | S20: 0 | T20: 0 | U20: 0 | V20: 0
C21: xxx | D21: 0 | E21: 0 | F21: 0 | G21: 0 | H21: 0 | I21: 0 | J21: 0 | K21: 0 | L21: 0 | M21: 0 | N21: 0 | O21: 0 | P21: 0 | Q21: 0 | R21: 0 | S21: 0 | T21: 0 | U21: 0 | V21: 0
C22: xxx | D22: 0 | E22: 0 | F22: 0 | G22: 0 | H22: 0 | I22: 0 | J22: 0 | K22: 0 | L22: 0 | M22: 0 | N22: 0 | O22: 0 | P22: 0 | Q22: 0 | R22: 0 | S22: 0 | T22: 0 | U22: 0 | V22: 0
E23: =SUM(E8:E22) -> 3.25 | H23: =SUM(H8:H22) -> 0.148035 | J23: =SUM(J8:J22) -> 0.0864 | L23: =SUM(L8:L22) -> 0.11485 | N23: =SUM(N8:N22) -> 0.047145 | P23: =SUM(P8:P22) -> 0.006495 | R23: =SUM(R8:R22) -> 0 | T23: =SUM(T8:T22) -> 0 | V23: =SUM(V8:V22) -> 0.006495
B24: Costo laboral Enero | E24: 25529425
K25: Cotizacion dólar | N25: 1465 | O25: 46053
B26: ASIGNACION TOTAL HORAS OPERACION | F26: =SUM(E8:E22)/8 -> 0.40625
B27: ASIGNACION TOTAL $$$ OPERACION | F27: =SUM(F8:F22) -> 0.40942 | I27: =E24*F27 -> 10452257 | M27: =I27/N25 -> 7134.6465
B29: ASIGNACION TOTAL HORAS COOPTECH | F29: =1-F26 -> 0.59375
B30: ASIGNACION TOTAL $$$ COOPTECH | F30: =1-F27 -> 0.59058 | I30: =E24*F30 -> 15077168 | M30: =I30/N25 -> 10291.582
B32: HORAS I+D A ACTIVAR | F32: =(8-(E23-E8-E11))/8 -> 0.7125 | I32: =I30*F32 -> 10742482 | M32: =M30*F32 -> 7332.7522 | P32: LAS HORAS A ACTIVAR SON UN PORCENTAJE DE LAS HORAS DESIGNADAS A PROYECTOS DE COOPTECH
B33: HORAS ASIGNADAS A GASTO | I33: =I30-I32 -> 4334685.7 | M33: =M30-M32 -> 2958.8298
Y34: OPERACIÓN COOPMORTEROS - Hace referencia a la cantidad del tiempo que el personal de IT esta disponible para soportar y mantener las unidades de negocio que ya se encuentran operativas y facturando.
G35: =$E$54*H53 -> 3992455.1 | I35: =$E$54*J53 -> 2390239.2 | K35: =$E$54*L53 -> 850018.3 | M35: =$E$54*N53 -> 2438939.6 | O35: =$E$54*P53 -> 0 | Q35: =$E$54*R53 -> 0 | S35: =$E$54*T53 -> 164853.73 | U35: =$E$54*V53 -> 0
D36: Costo Laboral % | E36: Horas asignadas | F36: Asignado $$ operación | G36: Adm. | I36: Energia | K36: Agua | M36: Tele. | O36: Canal 50 | Q36: CAC | S36: Alm. Taller. | U36: Serv. Sociales
G37: Hs. Asignadas | H37: Impacto $$ | I37: Hs. Asignadas | J37: Impacto $$ | K37: Hs. Asignadas | L37: Impacto $$ | M37: Hs. Asignadas | N37: Impacto $$ | O37: Hs. Asignadas | P37: Impacto $$ | Q37: Hs. Asignadas | R37: Impacto $$ | S37: Hs. Asignadas | T37: Impacto $$ | U37: Hs. Asignadas | V37: Impacto $$
Y38: Semana 1 - 03 al 07 | Z38: Semana 2 - 10 al 14 | AA38: Semana 3 - 17 al 21 | AB38: Semana 4 - 24 al 28
B39: Febrero 2026 | C39: Leonardo Depetris | D39: 0.2035 | E39: 0.6 | F39: 0.1221 | G39: 0.3 | H39: 0.06105 | I39: 0.2 | J39: 0.0407 | K39: 0.1 | L39: 0.02035 | M39: 0 | N39: 0 | O39: 0 | P39: 0 | Q39: 0 | R39: 0 | S39: 0 | T39: 0 | U39: 0 | V39: 0 | Y39: Medidores de energía Itron / Tabla Reconecta / Reparación IdP recuperadas Cooper | Z39: Armado Kits clientes Cooptech / Charla-Taller Cooptech / Evaluaciones de desempeño | AA39: Metodología KanBan / demo +Agua | AB39: Reunionces comerciales / Implementación Ucacha / Mejoras bombeo agua cruda
C40: Claudio Bottero | D40: 0.1503 | E40: 0.4 | F40: 0.06012 | G40: 0.2 | H40: 0.03006 | I40: 0 | J40: 0 | K40: 0 | L40: 0 | M40: 0.2 | N40: 0.03006 | O40: 0 | P40: 0 | Q40: 0 | R40: 0 | S40: 0 | T40: 0 | U40: 0 | V40: 0 | Y40: Server facturas porteña / nodos k8s / mqtt energia / viaje miramar | Z40: Actualizaciones varias / clientes coopcloud | AA40: Actualizaciones server MQTT | AB40: Limpieza VMs PMX / Implementación Ucacha / Agente Procoop / Rancher / VMs mutual
C41: Carola Clausen | D41: 0.1016 | E41: 0 | F41: 0 | G41: 0 | H41: 0 | I41: 0 | J41: 0 | K41: 0 | L41: 0 | M41: 0 | N41: 0 | O41: 0 | P41: 0 | Q41: 0 | R41: 0 | S41: 0 | T41: 0 | U41: 0 | V41: 0 | Y41: Ventas cooptech | Z41: Ventas cooptech | AA41: Ventas cooptech | AB41: Ventas cooptech
C42: Lorenzo Depetris | D42: 0.149 | E42: 0.3 | F42: 0.0447 | G42: 0 | H42: 0 | I42: 0.3 | J42: 0.0447 | K42: 0 | L42: 0 | M42: 0 | N42: 0 | O42: 0 | P42: 0 | Q42: 0 | R42: 0 | S42: 0 | T42: 0 | U42: 0 | V42: 0 | Y42: Ticket maniobra reconectadores | Z42: Viaje Santa Rosa / Armado Kits clientes Cooptech / Charla-Taller Cooptech / Actualización devoto | AA42: Accesorio Relé / Revision reco Marconi | AB42: Implementación Ucacha
C43: Juan Gonzalez | D43: 0.1427 | E43: 0.4 | F43: 0.05708 | G43: 0 | H43: 0 | I43: 0 | J43: 0 | K43: 0 | L43: 0 | M43: 0.4 | N43: 0.05708 | O43: 0 | P43: 0 | Q43: 0 | R43: 0 | S43: 0 | T43: 0 | U43: 0 | V43: 0 | Y43: Coopate / Alarmas deadmen / Provision | Z43: Provision / Charla-Taller Cooptech / Reconecta | AA43: Reconecta | AB43: Provision: plan empresa
C44: Julieta Costamagna | D44: 0.0937 | E44: 0.55 | F44: 0.051535 | G44: 0.55 | H44: 0.051535 | I44: 0 | J44: 0 | K44: 0 | L44: 0 | M44: 0 | N44: 0 | O44: 0 | P44: 0 | Q44: 0 | R44: 0 | S44: 0 | T44: 0 | U44: 0 | V44: 0 | Y44: Proveedores / Recupero de materiales / Acueducto / O.V. V.T. / API WISE | Z44: O.V. Pña / Adelantos / Recupero materiales / API WISE | AA44: Analitics Cooptech / Centinela | AB44: Centinela / OV.V V.T. / Acueducto / Proveedores
C45: Agustin Aressi | D45: 0.1002 | E45: 0.1 | F45: 0.01002 | G45: 0 | H45: 0 | I45: 0 | J45: 0 | K45: 0.1 | L45: 0.01002 | M45: 0 | N45: 0 | O45: 0 | P45: 0 | Q45: 0 | R45: 0 | S45: 0 | T45: 0 | U45: 0 | V45: 0 | Y45: +Agua: tablero rio 3° / Ajustes gráficas | Z45: +Agua: version mobile y nabvar | AA45: +Agua: version mobile y nabvar | AB45: Más Agua: ajustes de usuario
C46: Matías Gandino | D46: 0.0589 | E46: 0.1 | F46: 0.00589 | G46: 0 | H46: 0 | I46: 0 | J46: 0 | K46: 0 | L46: 0 | M46: 0 | N46: 0 | O46: 0 | P46: 0 | Q46: 0 | R46: 0 | S46: 0.1 | T46: 0.00589 | U46: 0 | V46: 0 | Y46: Analizadores de red | Z46: Analizadores de red / Actualización Devoto | AA46: Centralita generadores | AB46: Implementación Ucacha
C47: xxx | D47: 0 | E47: 0 | F47: 0 | G47: 0 | H47: 0 | I47: 0 | J47: 0 | K47: 0 | L47: 0 | M47: 0 | N47: 0 | O47: 0 | P47: 0 | Q47: 0 | R47: 0 | S47: 0 | T47: 0 | U47: 0 | V47: 0
C48: xxx | D48: 0 | E48: 0 | F48: 0 | G48: 0 | H48: 0 | I48: 0 | J48: 0 | K48: 0 | L48: 0 | M48: 0 | N48: 0 | O48: 0 | P48: 0 | Q48: 0 | R48: 0 | S48: 0 | T48: 0 | U48: 0 | V48: 0
C49: xxx | D49: 0 | E49: 0 | F49: 0 | G49: 0 | H49: 0 | I49: 0 | J49: 0 | K49: 0 | L49: 0 | M49: 0 | N49: 0 | O49: 0 | P49: 0 | Q49: 0 | R49: 0 | S49: 0 | T49: 0 | U49: 0 | V49: 0
C50: xxx | D50: 0 | E50: 0 | F50: 0 | G50: 0 | H50: 0 | I50: 0 | J50: 0 | K50: 0 | L50: 0 | M50: 0 | N50: 0 | O50: 0 | P50: 0 | Q50: 0 | R50: 0 | S50: 0 | T50: 0 | U50: 0 | V50: 0
C51: xxx | D51: 0 | E51: 0 | F51: 0 | G51: 0 | H51: 0 | I51: 0 | J51: 0 | K51: 0 | L51: 0 | M51: 0 | N51: 0 | O51: 0 | P51: 0 | Q51: 0 | R51: 0 | S51: 0 | T51: 0 | U51: 0 | V51: 0
C52: xxx | D52: 0 | E52: 0 | F52: 0 | G52: 0 | H52: 0 | I52: 0 | J52: 0 | K52: 0 | L52: 0 | M52: 0 | N52: 0 | O52: 0 | P52: 0 | Q52: 0 | R52: 0 | S52: 0 | T52: 0 | U52: 0 | V52: 0
E53: =SUM(E39:E52) -> 2.45 | H53: =SUM(H39:H52) -> 0.142645 | J53: =SUM(J39:J52) -> 0.0854 | L53: =SUM(L39:L52) -> 0.03037 | N53: =SUM(N39:N52) -> 0.08714 | P53: =SUM(P39:P52) -> 0 | R53: =SUM(R39:R52) -> 0 | T53: =SUM(T39:T52) -> 0.00589 | V53: =SUM(V39:V52) -> 0
B54: Costo laboral Febrero | E54: 27988749
K55: Cotizacion dólar | N55: 1084.25 | O55: 45716
B56: ASIGNACION TOTAL HORAS OPERACION | F56: =SUM(E39:E52)/8 -> 0.30625
B57: ASIGNACION TOTAL $$$ OPERACION | F57: =SUM(F39:F52) -> 0.351445 | I57: =E54*F57 -> 9836505.9 | M57: =I57/N55 -> 9072.1751
B59: ASIGNACION TOTAL HORAS COOPTECH | F59: =1-F56 -> 0.69375
B60: ASIGNACION TOTAL $$$ COOPTECH | F60: =1-F57 -> 0.648555 | I60: =E54*F60 -> 18152243 | M60: =I60/N55 -> 16741.751
B62: HORAS I+D A ACTIVAR | F62: =(8-(E53-E39-E41))/8 -> 0.76875 | I62: =I60*F62 -> 13954537 | M62: =M60*F62 -> 12870.221 | P62: LAS HORAS A ACTIVAR SON UN PORCENTAJE DE LAS HORAS DESIGNADAS A PROYECTOS DE COOPTECH
B63: HORAS ASIGNADAS A GASTO | I63: =I60-I62 -> 4197706.2 | M63: =M60-M62 -> 3871.5298
G65: =$E$84*H83 -> 6051050.9 | I65: =$E$84*J83 -> 342945.53 | K65: =$E$84*L83 -> 1235205.2 | M65: =$E$84*N83 -> 4894536 | O65: =$E$84*P83 -> 0 | Q65: =$E$84*R83 -> 0 | S65: =$E$84*T83 -> 344403.32 | U65: =$E$84*V83 -> 0
D66: Costo Laboral % | E66: Horas asignadas | F66: Asignado $$ operación | G66: Adm. | I66: Energia | K66: Agua | M66: Tele. | O66: Canal 50 | Q66: CAC | S66: Alm. Taller. | U66: Serv. Sociales
G67: Hs. Asignadas | H67: Impacto $$ | I67: Hs. Asignadas | J67: Impacto $$ | K67: Hs. Asignadas | L67: Impacto $$ | M67: Hs. Asignadas | N67: Impacto $$ | O67: Hs. Asignadas | P67: Impacto $$ | Q67: Hs. Asignadas | R67: Impacto $$ | S67: Hs. Asignadas | T67: Impacto $$ | U67: Hs. Asignadas | V67: Impacto $$
Y68: Semana 1 - 03 al 07 | Z68: Semana 2 - 10 al 14 | AA68: Semana 3 - 17 al 21 | AB68: Semana 4 - 24 al 28
B69: Marzo 2026 | C69: Leonardo Depetris | D69: 0.2019 | E69: =SUM(G69,I69,K69,M69,O69,Q69,S69,U69) -> 0.25 | F69: =D69*E69 -> 0.050475 | G69: 0.2 | H69: =G69*D69 -> 0.04038 | I69: 0 | J69: =I69*D69 -> 0 | K69: 0.05 | L69: =K69*D69 -> 0.010095 | M69: 0 | N69: =M69*D69 -> 0 | O69: 0 | P69: =O69*D69 -> 0 | Q69: 0 | R69: =Q69*D69 -> 0 | S69: 0 | T69: =S69*D69 -> 0 | U69: 0 | V69: =U69*D69 -> 0 | Y69: Reuniones de alianzas comerciales/ desarrollos varios Cooptech | Z69: Desarrollo Agua Potable / Automatización Castelli | AA69: Automatización Castelli / Capacitación LV Redes e implementación en Rio 3° | AB69: Reuniones comerciales / Ev. de desempeño / Seguimiento Castelli
C70: Claudio Bottero | D70: 0.1886 | E70: =SUM(G70,I70,K70,M70,O70,Q70,S70,U70) -> 0.6 | F70: =D70*E70 -> 0.11316 | G70: 0.45 | H70: =G70*D70 -> 0.08487 | I70: 0 | J70: =I70*D70 -> 0 | K70: 0 | L70: =K70*D70 -> 0 | M70: 0.15 | N70: =M70*D70 -> 0.02829 | O70: 0 | P70: =O70*D70 -> 0 | Q70: 0 | R70: =Q70*D70 -> 0 | S70: 0 | T70: =S70*D70 -> 0 | U70: 0 | V70: =U70*D70 -> 0 | Y70: VMs influx / server Prometheus / streaming / Actualización Procoop / VM mutuales / limpieza Proxmox | Z70: Server y backup Procoop / migración red interna / tickets IT | AA70: VMs proxmox CSPM + CoopCloud / Bateríasshelter 10J | AB70: Ticket Radio Rep. / Tickets rendimiento coopcloud / Server Integra Procoop
C71: Carola Clausen | D71: 0.1146 | E71: =SUM(G71,I71,K71,M71,O71,Q71,S71,U71) -> 0 | F71: =D71*E71 -> 0 | G71: 0 | H71: =G71*D71 -> 0 | I71: 0 | J71: =I71*D71 -> 0 | K71: 0 | L71: =K71*D71 -> 0 | M71: 0 | N71: =M71*D71 -> 0 | O71: 0 | P71: =O71*D71 -> 0 | Q71: 0 | R71: =Q71*D71 -> 0 | S71: 0 | T71: =S71*D71 -> 0 | U71: 0 | V71: =U71*D71 -> 0 | Y71: Reuniones de Ventas Cooptech | Z71: Reuniones de Ventas Cooptech | AA71: Reuniones de Ventas Cooptech | AB71: Reuniones de Ventas Cooptech
C72: Lorenzo Depetris | D72: 0.1342 | E72: =SUM(G72,I72,K72,M72,O72,Q72,S72,U72) -> 0.09 | F72: =D72*E72 -> 0.012078 | G72: 0 | H72: =G72*D72 -> 0 | I72: 0.06 | J72: =I72*D72 -> 0.008052 | K72: 0.03 | L72: =K72*D72 -> 0.004026 | M72: 0 | N72: =M72*D72 -> 0 | O72: 0 | P72: =O72*D72 -> 0 | Q72: 0 | R72: =Q72*D72 -> 0 | S72: 0 | T72: =S72*D72 -> 0 | U72: 0 | V72: =U72*D72 -> 0 | Y72: Sensor de nivel RS485 /API DNP3 / Soporte redes eléctricas | Z72: API DNP3 / Soporte redes eléctricas | AA72: Proyecto piloto Rio 3° | AB72: Soporte tickes Reconecta Cooptech / Instalación Agua potable
C73: Juan Gonzalez | D73: 0.1343 | E73: =SUM(G73,I73,K73,M73,O73,Q73,S73,U73) -> 0.95 | F73: =D73*E73 -> 0.127585 | G73: 0 | H73: =G73*D73 -> 0 | I73: 0 | J73: =I73*D73 -> 0 | K73: 0 | L73: =K73*D73 -> 0 | M73: 0.95 | N73: =M73*D73 -> 0.127585 | O73: 0 | P73: =O73*D73 -> 0 | Q73: 0 | R73: =Q73*D73 -> 0 | S73: 0 | T73: =S73*D73 -> 0 | U73: 0 | V73: =U73*D73 -> 0 | Y73: Provision (plan empresa) | Z73: Provision (ONT instaladas) | AA73: Provision (ONT instaladas) | AB73: Provision (ONT instaladas) / Módulo suspensiones
C74: Julieta Costamagna | D74: 0.1057 | E74: =SUM(G74,I74,K74,M74,O74,Q74,S74,U74) -> 0.75 | F74: =D74*E74 -> 0.079275 | G74: 0.7 | H74: =G74*D74 -> 0.07399 | I74: 0 | J74: =I74*D74 -> 0 | K74: 0 | L74: =K74*D74 -> 0 | M74: 0.05 | N74: =M74*D74 -> 0.005285 | O74: 0 | P74: =O74*D74 -> 0 | Q74: 0 | R74: =Q74*D74 -> 0 | S74: 0 | T74: =S74*D74 -> 0 | U74: 0 | V74: =U74*D74 -> 0 | Y74: Facturas proveedores | Z74: Facturas proveedores / Centinela / OV VT | AA74: VACACIONES | AB74: Facturas proveedores / provision / prepaga / acueducto
C75: Agustin Aressi | D75: 0.0885 | E75: =SUM(G75,I75,K75,M75,O75,Q75,S75,U75) -> 0.3 | F75: =D75*E75 -> 0.02655 | G75: 0 | H75: =G75*D75 -> 0 | I75: 0 | J75: =I75*D75 -> 0 | K75: 0.3 | L75: =K75*D75 -> 0.02655 | M75: 0 | N75: =M75*D75 -> 0 | O75: 0 | P75: =O75*D75 -> 0 | Q75: 0 | R75: =Q75*D75 -> 0 | S75: 0 | T75: =S75*D75 -> 0 | U75: 0 | V75: =U75*D75 -> 0 | Y75: LICENCIA | Z75: MasAgua: autogestión dashboard | AA75: MasAgua: edición de variables especiales | AB75: MasAgua: indicadores múltivariable
C76: Matías Gandino | D76: 0.0324 | E76: =SUM(G76,I76,K76,M76,O76,Q76,S76,U76) -> 0.45 | F76: =D76*E76 -> 0.01458 | G76: 0 | H76: =G76*D76 -> 0 | I76: 0.1 | J76: =I76*D76 -> 0.00324 | K76: 0 | L76: =K76*D76 -> 0 | M76: 0 | N76: =M76*D76 -> 0 | O76: 0 | P76: =O76*D76 -> 0 | Q76: 0 | R76: =Q76*D76 -> 0 | S76: 0.35 | T76: =S76*D76 -> 0.01134 | U76: 0 | V76: =U76*D76 -> 0 | Y76: Monitoreo generadores | Z76: Monitoreo generadores / Gralf ET132 | AA76: FINALIZACIÓN DE CONTRATO | AB76: FINALIZACIÓN DE CONTRATO
C77: xxx | D77: 0 | E77: =SUM(G77,I77,K77,M77,O77,Q77,S77,U77) -> 0 | F77: =D77*E77 -> 0 | G77: 0 | H77: =G77*D77 -> 0 | I77: 0 | J77: =I77*D77 -> 0 | K77: 0 | L77: =K77*D77 -> 0 | M77: 0 | N77: =M77*D77 -> 0 | O77: 0 | P77: =O77*D77 -> 0 | Q77: 0 | R77: =Q77*D77 -> 0 | S77: 0 | T77: =S77*D77 -> 0 | U77: 0 | V77: =U77*D77 -> 0
C78: xxx | D78: 0 | E78: =SUM(G78,I78,K78,M78,O78,Q78,S78,U78) -> 0 | F78: =D78*E78 -> 0 | G78: 0 | H78: =G78*D78 -> 0 | I78: 0 | J78: =I78*D78 -> 0 | K78: 0 | L78: =K78*D78 -> 0 | M78: 0 | N78: =M78*D78 -> 0 | O78: 0 | P78: =O78*D78 -> 0 | Q78: 0 | R78: =Q78*D78 -> 0 | S78: 0 | T78: =S78*D78 -> 0 | U78: 0 | V78: =U78*D78 -> 0
C79: xxx | D79: 0 | E79: =SUM(G79,I79,K79,M79,O79,Q79,S79,U79) -> 0 | F79: =D79*E79 -> 0 | G79: 0 | H79: =G79*D79 -> 0 | I79: 0 | J79: =I79*D79 -> 0 | K79: 0 | L79: =K79*D79 -> 0 | M79: 0 | N79: =M79*D79 -> 0 | O79: 0 | P79: =O79*D79 -> 0 | Q79: 0 | R79: =Q79*D79 -> 0 | S79: 0 | T79: =S79*D79 -> 0 | U79: 0 | V79: =U79*D79 -> 0
C80: xxx | D80: 0 | E80: =SUM(G80,I80,K80,M80,O80,Q80,S80,U80) -> 0 | F80: =D80*E80 -> 0 | G80: 0 | H80: =G80*D80 -> 0 | I80: 0 | J80: =I80*D80 -> 0 | K80: 0 | L80: =K80*D80 -> 0 | M80: 0 | N80: =M80*D80 -> 0 | O80: 0 | P80: =O80*D80 -> 0 | Q80: 0 | R80: =Q80*D80 -> 0 | S80: 0 | T80: =S80*D80 -> 0 | U80: 0 | V80: =U80*D80 -> 0
C81: xxx | D81: 0 | E81: =SUM(G81,I81,K81,M81,O81,Q81,S81,U81) -> 0 | F81: =D81*E81 -> 0 | G81: 0 | H81: =G81*D81 -> 0 | I81: 0 | J81: =I81*D81 -> 0 | K81: 0 | L81: =K81*D81 -> 0 | M81: 0 | N81: =M81*D81 -> 0 | O81: 0 | P81: =O81*D81 -> 0 | Q81: 0 | R81: =Q81*D81 -> 0 | S81: 0 | T81: =S81*D81 -> 0 | U81: 0 | V81: =U81*D81 -> 0
C82: xxx | D82: 0 | E82: =SUM(G82,I82,K82,M82,O82,Q82,S82,U82) -> 0 | F82: =D82*E82 -> 0 | G82: 0 | H82: =G82*D82 -> 0 | I82: 0 | J82: =I82*D82 -> 0 | K82: 0 | L82: =K82*D82 -> 0 | M82: 0 | N82: =M82*D82 -> 0 | O82: 0 | P82: =O82*D82 -> 0 | Q82: 0 | R82: =Q82*D82 -> 0 | S82: 0 | T82: =S82*D82 -> 0 | U82: 0 | V82: =U82*D82 -> 0
E83: =SUM(E69:E82) -> 3.39 | H83: =SUM(H69:H82) -> 0.19924 | J83: =SUM(J69:J82) -> 0.011292 | L83: =SUM(L69:L82) -> 0.040671 | N83: =SUM(N69:N82) -> 0.16116 | P83: =SUM(P69:P82) -> 0 | R83: =SUM(R69:R82) -> 0 | T83: =SUM(T69:T82) -> 0.01134 | V83: =SUM(V69:V82) -> 0
B84: Costo laboral Marzo | E84: 30370663
K85: Cotizacion dólar | N85: 1093.5 | O85: 45747
B86: ASIGNACION TOTAL HORAS OPERACION | F86: =SUM(E69:E76)/8 -> 0.42375
B87: ASIGNACION TOTAL $$$ OPERACION | F87: =SUM(F69:F76) -> 0.423703 | I87: =E84*F87 -> 12868141 | M87: =I87/N85 -> 11767.847
B89: ASIGNACION TOTAL HORAS COOPTECH | F89: =1-F86 -> 0.57625
B90: ASIGNACION TOTAL $$$ COOPTECH | F90: =1-F87 -> 0.576297 | I90: =E84*F90 -> 17502522 | M90: =I90/N85 -> 16005.964
B92: HORAS I+D A ACTIVAR | F92: =(8-(E83-E69-E71))/8 -> 0.6075 | I92: =I90*F92 -> 10632782 | M92: =M90*F92 -> 9723.6233 | P92: LAS HORAS A ACTIVAR SON UN PORCENTAJE DE LAS HORAS DESIGNADAS A PROYECTOS DE COOPTECH
B93: HORAS ASIGNADAS A GASTO | I93: =I90-I92 -> 6869739.9 | M93: =M90-M92 -> 6282.341
G95: =$E$114*H113 -> 5270006.5 | I95: =$E$114*J113 -> 993605.65 | K95: =$E$114*L113 -> 2162553.5 | M95: =$E$114*N113 -> 3109888.3 | O95: =$E$114*P113 -> 297107.57 | Q95: =$E$114*R113 -> 148553.79 | S95: =$E$114*T113 -> 0 | U95: =$E$114*V113 -> 0
D96: Costo Laboral % | E96: Horas asignadas | F96: Asignado $$ operación | G96: Adm. | I96: Energia | K96: Agua | M96: Tele. | O96: Canal 50 | Q96: CAC | S96: Alm. Taller. | U96: Serv. Sociales
G97: Hs. Asignadas | H97: Impacto $$ | I97: Hs. Asignadas | J97: Impacto $$ | K97: Hs. Asignadas | L97: Impacto $$ | M97: Hs. Asignadas | N97: Impacto $$ | O97: Hs. Asignadas | P97: Impacto $$ | Q97: Hs. Asignadas | R97: Impacto $$ | S97: Hs. Asignadas | T97: Impacto $$ | U97: Hs. Asignadas | V97: Impacto $$
Y98: Semana 1 - 31 al 04 | Z98: Semana 2 - 07 al 11 | AA98: Semana 3 - 14 al 18 | AB98: Semana 4 - 21 al 25 | AC98: Semana 5 - 28 al 02
B99: Abril 2026 | C99: Leonardo Depetris | D99: 0.204 | E99: =SUM(G99,I99,K99,M99,O99,Q99,S99,U99) -> 0.2 | F99: =D99*E99 -> 0.0408 | G99: 0 | H99: 0 | I99: 0.2 | J99: 0.04 | K99: 0 | L99: 0 | M99: 0 | N99: 0 | O99: 0 | P99: 0 | Q99: 0 | R99: 0 | S99: 0 | T99: 0 | U99: 0 | V99: 0 | Y99: Investigación Multivac 8 / Manual Castelli | Z99: Reuniones comerciales y estratégicas Cooptech | AA99: Integración Itron / Presentaciones comerciales | AB99: Integración Iron / Tablas de eventos reconectadores / Reuniones comerciales
C100: Claudio Bottero | D100: 0.1451 | E100: =SUM(G100,I100,K100,M100,O100,Q100,S100,U100) -> 0.65 | F100: =D100*E100 -> 0.094315 | G100: 0.45 | H100: 0.07 | I100: 0 | J100: 0 | K100: 0 | L100: 0 | M100: 0.2 | N100: 0.03 | O100: 0 | P100: 0 | Q100: 0 | R100: 0 | S100: 0 | T100: 0 | U100: 0 | V100: 0 | Y100: Ajustes Proxmox / Bkp Procoop | Z100: Revision Proxmox / Problemas Integra (Procoop) / networking clientes cooptech | AA100: ILO HP / Config cliente Cloud (PASSO) | AB100: Análisis capacidad Proxmox / cámara biodigestor / Open WRT | AC100: Implementación Reconecta / Cámara biodigestor
C101: Carola Clausen | D101: 0.1158 | E101: =SUM(G101,I101,K101,M101,O101,Q101,S101,U101) -> 0 | F101: =D101*E101 -> 0 | G101: 0 | H101: 0 | I101: 0 | J101: 0 | K101: 0 | L101: 0 | M101: 0 | N101: 0 | O101: 0 | P101: 0 | Q101: 0 | R101: 0 | S101: 0 | T101: 0 | U101: 0 | V101: 0 | Y101: Reuniones de Ventas Cooptech | Z101: Reuniones de Ventas Cooptech | AA101: Reuniones de Ventas Cooptech | AB101: Reuniones de Ventas Cooptech | AC101: Reuniones de Ventas Cooptech
C102: Lorenzo Depetris | D102: 0.1366 | E102: =SUM(G102,I102,K102,M102,O102,Q102,S102,U102) -> 0.65 | F102: =D102*E102 -> 0.08879 | G102: 0 | H102: 0 | I102: 0 | J102: 0 | K102: 0.65 | L102: 0.09 | M102: 0 | N102: 0 | O102: 0 | P102: 0 | Q102: 0 | R102: 0 | S102: 0 | T102: 0 | U102: 0 | V102: 0 | Y102: LICENCIA | Z102: Fabricación sensores ultrasónicos cloro CSPM | AA102: Lector de pulsos / API DNP3 | AB102: Lector de pulsos | AC102: Lector de pulsos / Soporte clientes cooptech
C103: Juan Gonzalez | D103: 0.1495 | E103: =SUM(G103,I103,K103,M103,O103,Q103,S103,U103) -> 0.76 | F103: =D103*E103 -> 0.11362 | G103: 0.1 | H103: 0.01 | I103: 0 | J103: 0 | K103: 0 | L103: 0 | M103: 0.66 | N103: 0.1 | O103: 0 | P103: 0 | Q103: 0 | R103: 0 | S103: 0 | T103: 0 | U103: 0 | V103: 0 | Y103: ONT Instaladas: en traslados | Z103: ONT Instaladas: en traslados / carga manual | AA103: ONT Instaladas: ajustes /Módulo mis facturas | AB103: Reconecta: filtros nuevos / tabla optimizada / alarmas deadmen | AC103: Provision: ajustes / Módulo Facturas O.V. / Reconecta: optimización eventos
C104: Julieta Costamagna | D104: 0.1217 | E104: =SUM(G104,I104,K104,M104,O104,Q104,S104,U104) -> 0.85 | F104: =D104*E104 -> 0.103445 | G104: 0.7 | H104: 0.09 | I104: 0 | J104: 0 | K104: 0 | L104: 0 | M104: 0 | N104: 0 | O104: 0.1 | P104: 0.01 | Q104: 0.05 | R104: 0.01 | S104: 0 | T104: 0 | U104: 0 | V104: 0 | Y104: O.V. Proveedores / recupero de materiales / email | Z104: Recupero de materiales / Instalación PADs / API WISE | AA104: Módulo proveedores / Promo Las Tipas | AB104: Canal 50: publicidades / Módulo proveedores / acueducto | AC104: Acueducto / Parque solar
C105: Agustin Aressi | D105: 0.1273 | E105: =SUM(G105,I105,K105,M105,O105,Q105,S105,U105) -> 0.4 | F105: =D105*E105 -> 0.05092 | G105: 0.4 | H105: 0.05 | I105: 0 | J105: 0 | K105: 0 | L105: 0 | M105: 0 | N105: 0 | O105: 0 | P105: 0 | Q105: 0 | R105: 0 | S105: 0 | T105: 0 | U105: 0 | V105: 0 | Y105: MasAgua: Dashboard | Z105: MasAgua: Dashboard | AA105: MasAgua: Variables de estado múltiple | AB105: Módulo Loteo Puesta del Sol / Mas agua: ajustes | AC105: Módulo Loteo Puesta del Sol / Mas agua: LLM
C106: Matías Gandino | D106: 0 | E106: =SUM(G106,I106,K106,M106,O106,Q106,S106,U106) -> 0 | F106: =D106*E106 -> 0 | G106: 0 | H106: 0 | I106: 0 | J106: 0 | K106: 0 | L106: 0 | M106: 0 | N106: 0 | O106: 0 | P106: 0 | Q106: 0 | R106: 0 | S106: 0 | T106: 0 | U106: 0 | V106: 0
C107: xxx | D107: 0 | E107: =SUM(G107,I107,K107,M107,O107,Q107,S107,U107) -> 0 | F107: =D107*E107 -> 0 | G107: 0 | H107: 0 | I107: 0 | J107: 0 | K107: 0 | L107: 0 | M107: 0 | N107: 0 | O107: 0 | P107: 0 | Q107: 0 | R107: 0 | S107: 0 | T107: 0 | U107: 0 | V107: 0
C108: xxx | D108: 0 | E108: =SUM(G108,I108,K108,M108,O108,Q108,S108,U108) -> 0 | F108: =D108*E108 -> 0 | G108: 0 | H108: 0 | I108: 0 | J108: 0 | K108: 0 | L108: 0 | M108: 0 | N108: 0 | O108: 0 | P108: 0 | Q108: 0 | R108: 0 | S108: 0 | T108: 0 | U108: 0 | V108: 0
C109: xxx | D109: 0 | E109: =SUM(G109,I109,K109,M109,O109,Q109,S109,U109) -> 0 | F109: =D109*E109 -> 0 | G109: 0 | H109: 0 | I109: 0 | J109: 0 | K109: 0 | L109: 0 | M109: 0 | N109: 0 | O109: 0 | P109: 0 | Q109: 0 | R109: 0 | S109: 0 | T109: 0 | U109: 0 | V109: 0
...

Sheet asientos
A2: 46023
A3: Activacion de Hs | B3: =+Asignacion!I32 -> 10742482
A4: Venta Interna Energia | B4: =+Asignacion!I4 -> 2205742.3
A5: Venta Interna Agua | B5: =+Asignacion!K4 -> 2932054.4
A6: Venta Interna Telecomunicaciones | B6: =+Asignacion!M4 -> 1203584.7
A7: Venta Interna Canal 50 | B7: =+Asignacion!O4 -> 165813.61
A8: Venta Interna Administracion | B8: =+Asignacion!G4 -> 3779248.4
A9: Venta Interna Serv. Sociales | B9: =+Asignacion!U4 -> 165813.61
A11: 46054
A12: Activacion de Hs | B12: =+Asignacion!I62 -> 13954537
A13: Venta Interna Energia | B13: =+Asignacion!I35 -> 2390239.2
A14: Venta Interna Agua | B14: =+Asignacion!K35 -> 850018.3
A15: Venta Interna Telecomunicaciones | B15: =+Asignacion!M35 -> 2438939.6
A16: Venta Interna Canal 50 | B16: =+Asignacion!O13 -> 0
A17: Venta Interna Administracion | B17: =+Asignacion!G35+Asignacion!S35 -> 4157308.8
A18: Venta Interna Serv. Sociales | B18: =+Asignacion!U13 -> 0
A20: 46082
A21: Activacion de Hs | B21: =+Asignacion!I92 -> 10632782
A22: Venta Interna Energia | B22: =+Asignacion!I65 -> 342945.53
A23: Venta Interna Agua | B23: =+Asignacion!K65 -> 1235205.2
A24: Venta Interna Telecomunicaciones | B24: =+Asignacion!M65 -> 4894536
A25: Venta Interna Canal 50 | B25: =+Asignacion!O22 -> 0
A26: Venta Interna Administracion | B26: =+Asignacion!G65+Asignacion!S65 -> 6395454.2
A27: Venta Interna Serv. Sociales | B27: =+Asignacion!U22 -> 0
A29: 46113
A30: Activacion de Hs | B30: =+Asignacion!I122 -> 6522888.6
A31: Venta Interna Energia | B31: =+Asignacion!I95 -> 993605.65
A32: Venta Interna Agua | B32: =+Asignacion!K95 -> 2162553.5
A33: Venta Interna Telecomunicaciones | B33: =+Asignacion!M95 -> 3109888.3
A34: Venta Interna Canal 50 | B34: =+Asignacion!O95 -> 297107.57
A35: Venta Interna Administracion | B35: =+Asignacion!G95+Asignacion!Q95 -> 5418560.2
A36: Venta Interna Serv. Sociales | B36: =+Asignacion!U31 -> 0
A39: 46143
A40: Activacion de Hs | B40: =+Asignacion!I152 -> 7629316.5
A41: Venta Interna Energia | B41: =+Asignacion!I125 -> 4109248.3
A42: Venta Interna Agua | B42: =+Asignacion!K125 -> 1446895
A43: Venta Interna Telecomunicaciones | B43: =+Asignacion!M125 -> 646856.96
A44: Venta Interna Canal 50 | B44: =+Asignacion!O125 -> 384062.65
A45: Venta Interna Administracion | B45: =+Asignacion!G125 -> 8137466.1
A46: Venta Interna Serv. Sociales | B46: =+Asignacion!U41 -> 0
